{
    "-h, --help     ": "display this help and exit",
    "-v, --version  ": "output version information and exit",
    "-r, --repo     ": "name of repository",
    "-o, --owner    ": "owner of repository",
    "-t, --tag      ": "tag of repository (should exist!)",
    "-f, --filename ": "path to asset",
    "-k, --token    ": "github token <https://github.com/settings/tokens/new>",
    "-l, --loud     ": "output filename, repo, owner and tag before upload",
    "--show-url     ": "show asset url",
    "--force        ": "overwrite asset if one with same name already exist"
}
